exo_language/__init__.py
exo_language/exo.py
exo_language/exo_classes/exo_classes.py
exo_language/exo_classes/exo_context.py
exo_language/exo_classes/exo_node.py
exo_language/exo_classes/exo_token.py
exo_language/exo_errors/exo_errors.py
exo_language/exo_examples/calculator.exo
exo_language/exo_examples/hello_world.exo
exo_language/exo_examples/project_euler_1.exo
exo_language/exo_examples/recursive_fibonacci.exo
exo_language/exo_utils/exo_interpreter.py
exo_language/exo_utils/exo_lexer.py
exo_language/exo_utils/exo_parser.py
exo_language/exo_utils/exo_runner.py
exo_language/exo_utils/grammar.txt
exo_language-0.1.4.dist-info/entry_points.txt
exo_language-0.1.4.dist-info/WHEEL
exo_language-0.1.4.dist-info/METADATA
exo_language-0.1.4.dist-info/RECORD
