Metadata-Version: 2.1
Name: exo-language
Version: 0.1.4
Summary: A programming language designed to be simple and fast, written in python
Home-page: https://github.com/supercoder186/Exo
Author: supercoder186
Author-email: aadit.kolar@gmail.com
Requires-Python: >=3.5,<4.0
Classifier: Programming Language :: Python :: 3
Classifier: Programming Language :: Python :: 3.5
Classifier: Programming Language :: Python :: 3.6
Classifier: Programming Language :: Python :: 3.7
Classifier: Programming Language :: Python :: 3.8
Classifier: Programming Language :: Python :: 3.9
Project-URL: Repository, https://github.com/supercoder186/Exo
